CHANGELOG.txt
LICENSE.txt
MANIFEST.in
Readme.txt
setup.py
DivideiteSolver.egg-info/PKG-INFO
DivideiteSolver.egg-info/SOURCES.txt
DivideiteSolver.egg-info/dependency_links.txt
DivideiteSolver.egg-info/top_level.txt
DivideiteSolvers.egg-info/SOURCES.txt
DivideiteSolvers.egg-info/dependency_links.txt
DivideiteSolvers.egg-info/top_level.txt
divideiteSolvers/__init__.py
divideiteSolvers/errors/__init__.py
divideiteSolvers/errors/errors.py